promptinject/__init__.py
promptinject/_utils.py
promptinject/prompt_data.py
promptinject/prompting.py
promptinject/run.py
promptinject/scoring.py
promptinject/visualization.py
promptinject-0.1.1.1.dist-info/LICENSE
promptinject-0.1.1.1.dist-info/METADATA
promptinject-0.1.1.1.dist-info/WHEEL
promptinject-0.1.1.1.dist-info/RECORD
