Metadata-Version: 2.1
Name: promptinject
Version: 0.1.1.1
Summary: PromptInject is a framework that assembles prompts in a modular fashion to provide a quantitative analysis of the robustness of LLMs to adversarial prompt attacks.
Home-page: https://github.com/agencyenterprise/PromptInject
License: MIT
Keywords: nlp,ai-safety,language-models
Author: Fabio Perez
Author-email: fabioperez@users.noreply.github.com
Requires-Python: >=3.8,<4.0
Classifier: License :: OSI Approved :: MIT License
Classifier: Programming Language :: Python :: 3
Classifier: Programming Language :: Python :: 3.8
Classifier: Programming Language :: Python :: 3.9
Classifier: Programming Language :: Python :: 3.10
Classifier: Programming Language :: Python :: 3.11
Classifier: Programming Language :: Python :: 3.12
Requires-Dist: openai (>=1.11.1,<2.0.0)
Requires-Dist: pandas (>=1.5.1,<2.0.0)
Requires-Dist: rapidfuzz (>=3.0.0,<4.0.0)
Requires-Dist: tqdm (>=4.64.1,<5.0.0)
Project-URL: Repository, https://github.com/agencyenterprise/PromptInject
